__init__.py
main.py
ui.py
the_antivirus-0.1.9.dist-info/licenses/LICENSE
the_antivirus-0.1.9.dist-info/METADATA
the_antivirus-0.1.9.dist-info/WHEEL
the_antivirus-0.1.9.dist-info/entry_points.txt
the_antivirus-0.1.9.dist-info/top_level.txt
the_antivirus-0.1.9.dist-info/RECORD
